LICENSE
MANIFEST.in
README
setup.py
version.py
rask_njord_http/__init__.py
rask_njord_http.egg-info/PKG-INFO
rask_njord_http.egg-info/SOURCES.txt
rask_njord_http.egg-info/dependency_links.txt
rask_njord_http.egg-info/requires.txt
rask_njord_http.egg-info/top_level.txt