Metadata-Version: 1.0
Name: rask-njord-http
Version: 0.0.4
Summary: Rask HTTP Client
Home-page: https://gitlab.com/vikingmakt/rask_njord_http
Author: Umgeher Torgersen
Author-email: me@umgeher.org
License: https://gitlab.com/vikingmakt/rask_njord_http/raw/master/LICENSE
Platform: UNKNOWN
